Workbook

Sheet Map
A1: # | B1: Gap (documented finding) | C1: Population in gap | D1: Population basis (source / derived) | E1: NIS at stake (source) | F1: Blocking mechanism | G1: Responsible body | H1: Fixed? | I1: Buildable (1–5) | J1: Unfixed factor | K1: Score | L1: Rank | M1: Source report | N1: Page(s) | O1: Verbatim / key quote | P1: Verification status | Q1: Ombudsman overlay | R1: Kol Zchut overlay (2025 views) | S1: 3-way (Comptroller / Ombudsman / Kol Zchut) | T1: Notes | U1: PDF URL
A2: 1 | B2: Retirees not reached with information on their NII rights (ימי מידע) | C2: 432572 | D2: Derived: 'בשנים 2020-2025 פרשו כ-450,000' (p.14) − 17,428 who attended NII information days (p.15). Only 148,996 (33%) were invited (p.15; repeated p.20, p.55). | E2: n/q in source | F2: NII outreach capacity (BTL reply May 2026 cites COVID and the security situation, p.15); no national policy on retirement information; 707,000 elderly (56.5% of 1,252,000) live in towns without an App+60 centre (p.16); only 3,831 of 375,000 retirees 2020–24 (~1%) attended App+60 prep workshops (p.16). Retirees themselves name מיצוי זכויות as one of the three main areas retirement preparation should cover (p.19). | G2: המוסד לביטוח לאומי; המשרד לשוויון חברתי; משרד הרווחה | H2: N | I2: 4 | J2: =IFERROR(INDEX('Legend & Method'!$C$11:$C$14,MATCH(H2,'Legend & Method'!$B$11:$B$14,0)),"") -> 1 | K2: =IF(ISNUMBER(C2),C2*J2*I2,"n/q") -> 1730288 | L2: =IF(ISNUMBER(K2),RANK(K2,$K$2:$K$23),"—") -> 1 | M2: Comptroller special report 'בשיבה טובה?' Jun 2026 — ch. השמירה על רווחת האוכלוסייה המזדקנת | N2: 14, 15, 16, 19, 20 | O2: הזמין בט"ל רק 148,996 אזרחים ותיקים להשתתף בימי המידע שקיים בסניפיו. היקף מוזמנים זה מהווה כ-33% בלבד מכלל הפורשים באותן שנים. בפועל, השתתפו בימים אלו רק 17,428 משתתפים (המהווים כ-4% מכלל הפורשים באותן שנים) (p.15) | P2: PDF-VERIFIED verbatim (full PDF, 57 pp., read via your browser) | Q2: NII: 1,581 complaints 2025, 7% justified (R52 p.26). Elderly special report 2023: 12,882 complaints by 65+ (2019–mid-2022), 13.2% Holocaust survivors. | R2: זיקנה והזדקנות 1.06M views 2025 (#12, ↑2). Russian site top pages = קצבת זקנה / השלמת הכנסה. | S2: C ✔ / O ✔ / K ✔ | T2: Same population as rows on arnona-30% and electricity discount → one 'retiree rights checker' covers three findings. | U2: https://library.mevaker.gov.il/sites/DigitalLibrary/Documents/2026/Population-Aging/2026-Population-Aging-104.pdf
A3: 2 | B3: Citizens 60–75 without any retirement preparation | C3: 434000 | D3: Source figure (the report's own sample-based extrapolation): 'ניתן לשער כי כ-434,000 אזרחים בני 60-75 לא עברו הכנה לפרישה' (p.12); 77% of respondents; 63% among those already retired; low-income 105,000–185,000 (82%) (p.12). | E3: n/q in source | F3: 51% of non-participants: nobody offered it; 18% unaware programmes exist (p.13). Only 3,831 of 375,000 retirees (≈1%) attended App+60 workshops (p.16). | G3: משרד הרווחה; המשרד לשוויון חברתי; ביטוח לאומי | H3: N | I3: 2 | J3: =IFERROR(INDEX('Legend & Method'!$C$11:$C$14,MATCH(H3,'Legend & Method'!$B$11:$B$14,0)),"") -> 1 | K3: =IF(ISNUMBER(C3),C3*J3*I3,"n/q") -> 868000 | L3: =IF(ISNUMBER(K3),RANK(K3,$K$2:$K$23),"—") -> 2 | M3: Comptroller 'בשיבה טובה?' Jun 2026 — ch. 104 | N3: 12, 13, 16 | O3: 77% מכלל המשיבים לסקר אוכלוסיית האזרחים הוותיקים בגילי 60-75 … לא עברו הכנה לפרישה (p.12) | P3: PDF-VERIFIED verbatim | Q3: as above | R3: as above | S3: C ✔ / O – / K ✔ | T3: Informational gap, not a cash entitlement — buildable only as a guide; scored low on buildability on purpose. | U3: https://library.mevaker.gov.il/sites/DigitalLibrary/Documents/2026/Population-Aging/2026-Population-Aging-104.pdf
A4: 3 | B4: Eligible households not receiving the electricity tariff discount | C4: 158000 | D4: Source figure: 'כ-158,000 זכאים אינם מקבלים הנחות בחשבון החשמל, ובהם ניצולי שואה וחיילים בודדים (מתוך כ-471,000 זכאים)' (p.1209; body p.1282). Uptake fell 67% (2016) → 64% (2022) (p.1209). Of the 158,000, 4,959 ARE IEC customers and still don't get it (Nov 2022, p.1283). | E4: n/q (discount value per household not stated) | F4: Discount is automatic only when the eligible person's ID/name matches an IEC customer record (p.1283); most non-recipients have no IEC contract in their own name (p.1209) and IEC says approaching non-customers is 'operationally and legally complex' and not its responsibility (p.1283). Lowest uptake: families with 4+ children 20–22%, lone soldiers 24–26%; Holocaust-survivor uptake declining 2016–22 (table p.1287). | G4: חברת החשמל; המוסד לביטוח לאומי; צה"ל (חיילים בודדים); רשות החשמל | H4: Unknown | I4: 4 | J4: =IFERROR(INDEX('Legend & Method'!$C$11:$C$14,MATCH(H4,'Legend & Method'!$B$11:$B$14,0)),"") -> 0.75 | K4: =IF(ISNUMBER(C4),C4*J4*I4,"n/q") -> 474000 | L4: =IF(ISNUMBER(K4),RANK(K4,$K$2:$K$23),"—") -> 3 | M4: Comptroller annual 74א, Jan 2024 — השירות לציבור בחברת החשמל | N4: 1209, 1281–1283, 1287, 1298 | O4: כ-158,000 זכאים אינם מקבלים הנחות בחשבון החשמל, ובהם ניצולי שואה וחיילים בודדים (מתוך כ-471,000 זכאים). שיעור המיצוי נמוך במיוחד בקבוצת הזכאים של משפחות עם ארבעה ילדים (p.1209) | P4: PDF-VERIFIED verbatim (full PDF, 96 pp.) | Q4: IEC: 558 complaints 2023 (R50-EN p.11–12); −38% in 2024 (R51 p.23). Not discount-specific. | R4: No dedicated topic; צרכנות 1.03M. Not in top-10 pages. | S4: C ✔✔ / O ~ / K – | T4: Actionable instruction for a tool: 'is the electricity contract in the eligible person's name? if not, transfer it' — then the discount is automatic by ID match. Eligible groups overlap heavily with the retiree cell. | U4: https://library.mevaker.gov.il/sites/DigitalLibrary/Documents/2024/2024.01-74A/2024-74A-303-Electric.pdf
A5: 4 | B5: Oct-7 'second circle' exposed to the attack with no legal entitlement | C5: 180000 | D5: Source figure: ~180,000 in the מעגל השני (pp.2–21); 61,100 recognised first-circle claims. | E5: ~₪1B TTR paid to Aug 2024 (first circle) | F5: No statutory entitlement without physical presence — legislative gap. | G5: ביטוח לאומי; משרד האוצר; משרד הביטחון (הרשות המאשרת) | H5: N | I5: 1 | J5: =IFERROR(INDEX('Legend & Method'!$C$11:$C$14,MATCH(H5,'Legend & Method'!$B$11:$B$14,0)),"") -> 1 | K5: =IF(ISNUMBER(C5),C5*J5*I5,"n/q") -> 180000 | L5: =IF(ISNUMBER(K5),RANK(K5,$K$2:$K$23),"—") -> 4 | M5: Comptroller special report Feb 2025 — הסדרת הסיוע לנפגעי פעולות איבה | N5: 2–21 (abstract) | O5: ~180,000 — as rendered | P5: Fetch-verified (abstract) | Q5: NII 1,581 (2025) | R5: מצב חירום 1.16M (↓3) | S5: C ✔ / O ~ / K ~ | T5: Nothing to match people to — excluded from recommendation despite population. | U5: https://library.mevaker.gov.il/sites/DigitalLibrary/Documents/2025/Swords-of-Iron-1/2025-Swords-of-Iron-300.pdf
A6: 5 | B6: Adults with disabilities eligible for Welfare services but not receiving them | C6: 19000 | D6: Derived: 44,500 eligible − 25,500 receiving (57%) in 2022 (p.2). Subset: ~3,700 (37%) special-ed graduates get no service (p.9). | E6: n/q | F6: Non-recognition (10% of מש"ה, 24% of autism not recognised); no referral pathway at graduation; 'community housing' never defined (p.10). | G6: משרד הרווחה; ביטוח לאומי; משרד החינוך | H6: N | I6: 3 | J6: =IFERROR(INDEX('Legend & Method'!$C$11:$C$14,MATCH(H6,'Legend & Method'!$B$11:$B$14,0)),"") -> 1 | K6: =IF(ISNUMBER(C6),C6*J6*I6,"n/q") -> 57000 | L6: =IF(ISNUMBER(K6),RANK(K6,$K$2:$K$23),"—") -> 5 | M6: Comptroller annual 75א ch.1, Jul 2024 — טיפול משרד הרווחה בבוגרים עם מוגבלות | N6: 2, 9, 10 | O6: יותר משליש (כ-3,700 איש שהם 37%) מבוגרי מערכת החינוך המיוחד שמשרד הרווחה מכיר בהם | P6: Fetch-verified verbatim (abstract) | Q6: משרד הרווחה complaints +69% in 2025 (R52 p.28), count n/q. | R6: אנשים עם מוגבלות 2.97M (#3) | S6: C ✔ / O ~ / K ✔ | T6: Services are capacity-constrained; a family-facing 'what you are entitled to after special-ed' guide helps at the margin. | U6: https://library.mevaker.gov.il/sites/DigitalLibrary/Documents/2024/2024.07-75A/2024.07-75A-102-Adults-W-Disabilities.pdf
A7: 6 | B7: Reservists paid only the minimum daily compensation | C7: 106000 | D7: Derived: one-third of ~318,000 mobilised Oct 2023–Jul 2024 (p.17–18); 57% of ~60,000 students (p.17). | E7: ₪311/day ≈ ₪9,300/month minimum; risk of reverting to ₪215/day | F7: Statutory rate, not a take-up failure; temporary increase needs legislation. | G7: משרד האוצר; ביטוח לאומי | H7: Partial | I7: 1 | J7: =IFERROR(INDEX('Legend & Method'!$C$11:$C$14,MATCH(H7,'Legend & Method'!$B$11:$B$14,0)),"") -> 0.5 | K7: =IF(ISNUMBER(C7),C7*J7*I7,"n/q") -> 53000 | L7: =IF(ISNUMBER(K7),RANK(K7,$K$2:$K$23),"—") -> 6 | M7: Comptroller special report Nov 2025 — reservists ch.1 | N7: 17, 18 (abstract) | O7: כשליש ממשרתי המילואים … קיבלו את סכום התגמול המזערי היומי (כ-311 ש"ח) | P7: Fetch-verified verbatim (abstract); compensation take-up ~99% per BTL (ch.1 p.19, PDF-verified) | Q7: as above | R7: as above | S7: C ✔ / O ✔ / K ✔✔ | T7: Not a rights-realisation gap; listed because it dominates the report. | U7: https://library.mevaker.gov.il/sites/DigitalLibrary/Documents/2025/Reservists/2025-Reservists-101-Benefit.pdf
A8: 7 | B8: Disabled IDF veterans unaware of their 'נפש אחת' benefits basket | C8: 11322 | D8: Derived lower bound: the 74%–80% 'unaware' figure comes from a questionnaire among veterans with head injury, mental injury or PTSD — ~15,300 of the ~60,000 recognised veterans (p.1475, p.1479) → 15,300 × 74% = 11,322. Not extrapolated to all 60,000. | E8: Reform budget 2021–22 ₪1.5B (incl. ₪300M one-off), executed ₪443M (30%) (p.1477) → ₪1.057B unexecuted (derived); PTSD: ₪461M budget, 14% executed (p.1476) | F8: Awareness (74–80% unaware of personal basket; 74–79% of family basket, p.1479); department cannot 'push' benefits — each claim needs manual documentation; 66% of posts filled; digital system never started. Report written before the war (p.1475). | G8: משרד הביטחון – אגף השיקום | H8: Unknown | I8: 4 | J8: =IFERROR(INDEX('Legend & Method'!$C$11:$C$14,MATCH(H8,'Legend & Method'!$B$11:$B$14,0)),"") -> 0.75 | K8: =IF(ISNUMBER(C8),C8*J8*I8,"n/q") -> 33966 | L8: =IF(ISNUMBER(K8),RANK(K8,$K$2:$K$23),"—") -> 7 | M8: Comptroller annual 74א, Jan 2024 — רפורמת 'נפש אחת' | N8: 1475, 1476, 1477, 1479, 1557 | O8: שיעור גבוה (74%-80%) של משיבים אינם מודעים לסל ההטבות האישי או מודעים רק לחלק ממנו, ושיעור דומה של משיבים (74%-79%) אינם מודעים לסל ההטבות לבני המשפחה (p.1479) | P8: PDF-VERIFIED verbatim (full PDF, 86 pp.) | Q8: R52 appendix p.130: משרד הביטחון 286 complaints 2025, 48% justified; of which אגף שיקום נכים 211, 53.2% justified (highest of the big bodies). | R8: אנשים עם מוגבלות 2.97M (#3) — not veteran-specific. | S8: C ✔✔ / O ~ / K ~ | T8: Sensitive population; population grew sharply after Oct 7. Content exists (MoD site, Kol Zchut). Strong #2 candidate. | U8: https://library.mevaker.gov.il/sites/DigitalLibrary/Documents/2024/2024.01-74A/2024-74A-401-Nefesh1.pdf
A9: 8 | B9: Daycare-subsidy (סבסוד מעונות) applicants mishandled | C9: 6931 | D9: Source figure: 6,931 complaints against האגף לעידוד תעסוקת הורים in 2025 (+740%), 90.8% justified (R52 pp.24, 26). Complaints, not population. | E9: n/q | F9: Call centre unavailable; extreme delays setting support grades; siblings graded differently; evacuee/reservist entitlements mishandled (R52 pp.70–86). | G9: משרד העבודה | H9: Unknown | I9: 3 | J9: =IFERROR(INDEX('Legend & Method'!$C$11:$C$14,MATCH(H9,'Legend & Method'!$B$11:$B$14,0)),"") -> 0.75 | K9: =IF(ISNUMBER(C9),C9*J9*I9,"n/q") -> 15594.75 | L9: =IF(ISNUMBER(K9),RANK(K9,$K$2:$K$23),"—") -> 8 | M9: Ombudsman annual report 52 (for 2025), May 2026 | N9: 24, 26, 70–86 | O9: 6,931 / 90.8% — per fetch of R52 chart 3 (RTL chart decoding, cross-checked with press release) | P9: Agent-decoded chart + press release; verify in PDF | Q9: This IS the Ombudsman signal (largest single body 2025). | R9: משפחה 1.05M (↑8) | S9: C – / O ✔✔ / K ✔ | T9: Backlog problem; a tool could only generate Ombudsman complaints / status checks. | U9: https://library.mevaker.gov.il/sites/DigitalLibrary/Documents/2026/2026-NTZ-52.pdf
A10: 9 | B10: Self-employed reservists in debt to BTL from compensation recalculation | C10: 4400 | D10: Source figure: 'בספטמבר 2024 היו לכ-4,400 משרתי מילואים עצמאים חובות בסך כ-37 מיליון שקלים … ומהם גבה כ-20 מיליון ש"ח באמצעות קיזוז' (ch.1 PDF p.24). | E10: ₪37M (Sep 2024), ₪20M of it already offset | F10: Compensation advanced on projected income; final 2023 assessments lower → debt (p.24). Fix: late-2024 law — higher-of calculation for 2023–24, debts cancelled; extended to 2025 (p.25 recommends a permanent arrangement beyond 2025). Take-up of compensation itself: BTL reported ~99% in Dec 2024 and the Comptroller commends its outreach (p.19). | G10: ביטוח לאומי; משרד האוצר | H10: Partial | I10: 3 | J10: =IFERROR(INDEX('Legend & Method'!$C$11:$C$14,MATCH(H10,'Legend & Method'!$B$11:$B$14,0)),"") -> 0.5 | K10: =IF(ISNUMBER(C10),C10*J10*I10,"n/q") -> 6600 | L10: =IF(ISNUMBER(K10),RANK(K10,$K$2:$K$23),"—") -> 9 | M10: Comptroller special report Nov 2025 — היבטים במענה למשרתי המילואים, ch.1 (2025-Reservists-101-Benefit.pdf) | N10: 19, 24, 25 | O10: לפי נתוני בט"ל, בספטמבר 2024 היו לכ-4,400 משרתי מילואים עצמאים חובות בסך כ-37 מיליון שקלים, כתוצאה מהתחשבנות בהתאם לשומות לשנת 2023, ומהם גבה כ-20 מיליון ש"ח באמצעות קיזוז (p.24) | P10: PDF-VERIFIED verbatim (ch.1 PDF, 56 pp.) | Q10: R52 appendix p.136: ביטוח לאומי 1,677 complaints 2025, 7.1% justified (36 of 505 decided). Chart 3 p.26: 1,581. | R10: מילואים 0.95M 2025 (#15, ↓7); 1.5M 2024 (#8) | S10: C ✔ / O ✔ / K ✔✔ | T10: Your candidate #1 — verified, but the debt was cancelled by law (temporary through 2025) and compensation take-up is ~99%. Gap closed; only the post-2025 permanence is open. | U10: https://library.mevaker.gov.il/sites/DigitalLibrary/Documents/2025/Reservists/2025-Reservists-101-Benefit.pdf
A11: 10 | B11: Public housing: eligible households waiting | C11: 4300 | D11: Source figure: 4,300 eligible waiting, avg 35 months (agent-reported from Jul 2024 ch. 204). | E11: n/q | F11: Stock fell 90k→48k; no units in Arab/Haredi towns. | G11: משרד הבינוי והשיכון; עמידר | H11: N | I11: 1 | J11: =IFERROR(INDEX('Legend & Method'!$C$11:$C$14,MATCH(H11,'Legend & Method'!$B$11:$B$14,0)),"") -> 1 | K11: =IF(ISNUMBER(C11),C11*J11*I11,"n/q") -> 4300 | L11: =IF(ISNUMBER(K11),RANK(K11,$K$2:$K$23),"—") -> 10 | M11: Comptroller annual 75א ch.1, Jul 2024 — דיור ציבורי: ביקורת מעקב | N11: n/v | O11: — | P11: Agent-reported — verify | Q11: עמידר complaints (elderly report 2023: 2,919 in 2019–21) | R11: דיור ושיכון 1.77M (↑1) | S11: C ✔ / O ✔ / K ✔ | T11: Supply-side. | U11: https://library.mevaker.gov.il/sites/DigitalLibrary/Documents/2024/2024.07-75A/2024.07-75A-204-Diyoor-Tziburi.pdf
A12: 11 | B12: Reservists' employment rights violated (dismissals, protections) | C12: 542 | D12: Source figure: 542 suspected employment-rights cases Oct 2023–May 2024 (≈4× the ~37/yr average); 244 dismissal-permit requests, 240 granted (p.17). Reported cases only. | E12: n/q | F12: Protections temporary (days 31–60 post-discharge protection expires end-2025, p.20); other-parent rights not publicised by IDF until Jul 2025 (ch.1 p.54). The Comptroller himself doubts a broad phenomenon: 'ספק אם ניתן להצביע … על תופעה רחבה של פגיעה בזכויות משרתי המילואים בעבודה' given ~217,000 employees (ch.1 p.51), while noting under-reporting for fear of employers. | G12: משרד הביטחון (ועדת התעסוקה); משרד העבודה; צה"ל; נציבות שוויון הזדמנויות בעבודה | H12: Unknown | I12: 4 | J12: =IFERROR(INDEX('Legend & Method'!$C$11:$C$14,MATCH(H12,'Legend & Method'!$B$11:$B$14,0)),"") -> 0.75 | K12: =IF(ISNUMBER(C12),C12*J12*I12,"n/q") -> 1626 | L12: =IF(ISNUMBER(K12),RANK(K12,$K$2:$K$23),"—") -> 11 | M12: Comptroller special report Nov 2025 — reservists ch.1 | N12: 17, 20, 51, 53, 54 | O12: 542 מספר המקרים שבהם עלה חשש לפגיעה בזכויות בעבודה (p.17) | P12: PDF-VERIFIED verbatim | Q12: as above | R12: as above | S12: C ✔ / O ✔ / K ✔✔ | T12: The state already built this tool: the Equal Opportunities Commission published a routing questionnaire and a digital rights guide for reservists and spouses in Jul 2024, and the Labour Ministry a chatbot (ch.1 p.53). Not a gap to fill. | U12: https://library.mevaker.gov.il/sites/DigitalLibrary/Documents/2025/Reservists/2025-Reservists-101-Benefit.pdf
A13: 12 | B13: Small businesses' war aid: claims unprocessed, fees to representatives | C13: 60000 | D13: ~60,000 claims (12%) unprocessed; only 9% of ≤₪300k businesses paid at first; ₪1.27B absorbed by representatives' fees (תקציר, Jun 2025). | E13: ₪1.27B fees | F13: Complex filing → paid representatives; processing backlog. | G13: רשות המסים; משרד הכלכלה; משרד האוצר | H13: Y | I13: 2 | J13: =IFERROR(INDEX('Legend & Method'!$C$11:$C$14,MATCH(H13,'Legend & Method'!$B$11:$B$14,0)),"") -> 0 | K13: =IF(ISNUMBER(C13),C13*J13*I13,"n/q") -> 0 | L13: =IF(ISNUMBER(K13),RANK(K13,$K$2:$K$23),"—") -> 12 | M13: Comptroller special report Jun 2025 — יישום הסיוע הכלכלי לעסקים קטנים | N13: תקציר (n/v) | O13: — | P13: Agent-reported from תקציר; not re-fetched | Q13: רשות המסים 1,119 complaints 2025 (+42%), 10% justified | R13: עצמאים ובעלי עסקים 1.08M (↑3) | S13: C ✔ / O ✔ / K ✔ | T13: Programme is time-bound and largely closed → factor 0. | U13: https://library.mevaker.gov.il/sites/DigitalLibrary/Documents/2025/Swords-of-Iron-3/2025.6-Small-Businesses-Taktzir.pdf
A14: 13 | B14: Arnona discounts/exemptions not received by eligible residents (all groups) | C14: n/q | D14: n/q — neither report counts eligible non-recipients. Scale: discounts & exemptions ₪7.382B in 2023 (Ombudsman p.10); ₪8.8B in 2020 (Comptroller 2023 p.245). | E14: ₪7.38B/yr total discounts (2023); unclaimed share n/q | F14: Annual re-application demanded from automatic-eligible groups; retroactive discounts refused; reservists denied on address mismatch (p.28); wrong age thresholds (p.27); irregular BTL data feeds (some councils yearly, 2023 report p.249); unlawful compound-discount handling; no appeals committees (p.250). | G14: רשויות מקומיות; משרד הפנים | H14: N | I14: 5 | J14: =IFERROR(INDEX('Legend & Method'!$C$11:$C$14,MATCH(H14,'Legend & Method'!$B$11:$B$14,0)),"") -> 1 | K14: =IF(ISNUMBER(C14),C14*J14*I14,"n/q") -> n/q | L14: =IF(ISNUMBER(K14),RANK(K14,$K$2:$K$23),"—") -> — | M14: Ombudsman special report Feb 2026 — תלונות הציבור בנושא ארנונה; Comptroller שלטון מקומי Jul 2023 — ארנונה: אסדרה, הטלה ומתן הנחות | N14: Ombudsman: 3, 10, 12–17, 24–39; Comptroller 2023: 245, 248–250 | O14: אוכלוסיות הזקוקות להנחות בארנונה לעיתים חשופות יותר לפערי מידע ולקשיי נגישות מול הרשויות (Ombudsman p.3) | P14: Fetch-verified (Ombudsman report fully visible, 43 pp.; Comptroller abstract pp.245–266) | Q14: Dedicated report: 937 complaints 1/2023–11/2025, 40% justified; 41.8% about discounts (41.6% justified); ₪376,508 recovered; local govt ≈20% of all 2025 complaints. | R14: Not in any published ranking (inside מיסים 3.21M / דיור 1.77M). | S14: C ✔ / O ✔✔ / K – | T14: Highest buildability in the map; population unquantified. The '₪3B' in your brief is an Israel Hayom headline, not in the report. | U14: https://library.mevaker.gov.il/sites/DigitalLibrary/Documents/2026/2026-Ombudsman-Arnona.pdf
A15: 14 | B15: Seniors receiving the 25% regulatory arnona discount instead of the 30% statutory one | C15: n/q | D15: n/q nationally. In 7 of 9 audited authorities (אלעד, אשקלון, נס ציונה, ערד, קריית ביאליק, שדות דן, תל מונד) 1%–5% of seniors held the 30% discount under חוק האזרחים הוותיקים while 18%–40% held the 25% regulatory discount (p.622; table on PDF p.92, e.g. Ashkelon: 39 seniors at 30% vs 4,375 at 25%). 1.16M seniors 65+ nationally (p.620). | E15: n/q (5 pp of the bill on up to 100 m²; law: income ≤ average wage, one-time written application — PDF p.91) | F15: 25% applied automatically by age; 30% requires a one-time application with income test; audited municipalities 'אינן מיידעות באופן יזום' seniors that they can apply (p.623); 84% of seniors report no proactive contact from their municipality (p.622); rights info on municipal websites 'אינו בולט ואינו זמין בקלות' (p.626). | G15: רשויות מקומיות; משרד הפנים; משרד הרווחה | H15: N | I15: 5 | J15: =IFERROR(INDEX('Legend & Method'!$C$11:$C$14,MATCH(H15,'Legend & Method'!$B$11:$B$14,0)),"") -> 1 | K15: =IF(ISNUMBER(C15),C15*J15*I15,"n/q") -> n/q | L15: =IF(ISNUMBER(K15),RANK(K15,$K$2:$K$23),"—") -> — | M15: Comptroller שלטון מקומי Jul 2023 — טיפול הרשויות המקומיות באזרחים הוותיקים | N15: 620, 622, 623, 626; body PDF pp.91–93 | O15: מספר האזרחים הוותיקים שמקבלים הנחה בשיעור של 30% מתוקף חוק האזרחים הוותיקים נמוך (בין 1% ל-5% מהאזרחים הוותיקים) ושיעור מקבלי הנחת אזרח ותיק בשיעור 25% מתוקף תקנות ההנחה בארנונה נע בין 18% ל-40% (p.622) | P15: PDF-VERIFIED verbatim (full PDF, 96 pp.) | Q15: Arnona report cases: wrong age threshold (Ashdod p.27), wrongful cancellation for elderly (Rishon p.30). Elderly report 2023 p.41: Interior Ministry asked to examine a digital platform pooling arnona-discount eligibility data (MoD, NII, survivors' authority, Aliyah) for all 255 municipalities; p.31: BTL study — 86% would apply 'if the process were simpler'. | R15: זיקנה 1.06M | S15: C ✔ / O ✔ / K ~ | T15: Single sharpest 'money left on the table' item for the retiree cell: 3 questions + a pre-filled request letter. | U15: https://library.mevaker.gov.il/sites/DigitalLibrary/Documents/2023/2023-Shilton/2023-Shilton-202-Vatikim.pdf
A16: 15 | B16: Seniors unaware of municipal services | C16: n/q | D16: n/q nationally (survey shares): 42% don't know municipal leisure services (p.621); <60% know any service; 84% never contacted proactively (p.622); day-centre uptake 9–30% (p.622). | E16: Under-spent 2021 welfare allocations in 6 audited municipalities, e.g. Ashkelon ₪4.89M at 90% (p.621) | F16: No proactive outreach; 32 municipalities (12.5%) never appointed a seniors' advisor. | G16: רשויות מקומיות; משרד הרווחה; המשרד לשוויון חברתי | H16: N | I16: 3 | J16: =IFERROR(INDEX('Legend & Method'!$C$11:$C$14,MATCH(H16,'Legend & Method'!$B$11:$B$14,0)),"") -> 1 | K16: =IF(ISNUMBER(C16),C16*J16*I16,"n/q") -> n/q | L16: =IF(ISNUMBER(K16),RANK(K16,$K$2:$K$23),"—") -> — | M16: Comptroller שלטון מקומי Jul 2023 — ch. 202 | N16: 621–622 | O16: 42% מהאזרחים הוותיקים לא מכירים את פעילויות הפנאי שמספקות הרשויות המקומיות | P16: Fetch-verified verbatim | Q16: Elderly special report 2023 (12,882 complaints) | R16: זיקנה 1.06M | S16: C ✔ / O ✔ / K ✔ | T16: Municipal programmes are not in Kol Zchut — content would have to be built per municipality; keep out of a 3-day scope. | U16: https://library.mevaker.gov.il/sites/DigitalLibrary/Documents/2023/2023-Shilton/2023-Shilton-202-Vatikim.pdf
A17: 16 | B17: Water-bill relief for disadvantaged households not reaching them | C17: n/q | D17: n/q. Budget 2015–2021 unused: ₪243M (~42%) per text p.1408–1409 vs ₪225M (~52%) in summary box p.1409 — internal inconsistency, flag. | E17: ₪225–243M unused 2015–2021 | F17: 'מנגנון הסיוע לאוכלוסיות ראויות לקידום אינו יעיל' — regulation never amended; follow-up: הליקוי לא תוקן (p.1409). | G17: רשות המים; משרד האוצר; תאגידי מים | H17: N | I17: 1 | J17: =IFERROR(INDEX('Legend & Method'!$C$11:$C$14,MATCH(H17,'Legend & Method'!$B$11:$B$14,0)),"") -> 1 | K17: =IF(ISNUMBER(C17),C17*J17*I17,"n/q") -> n/q | L17: =IF(ISNUMBER(K17),RANK(K17,$K$2:$K$23),"—") -> — | M17: Comptroller annual 74א, Jan 2024 — תאגידי המים והביוב: ביקורת מעקב | N17: 1408–1409 | O17: הליקוי לא תוקן: מנגנון הסיוע לא תוקן, ומשרד האוצר לא הגיש לוועדת הכספים הצעה לתיקון התקנות | P17: Fetch-verified verbatim | Q17: — | R17: — | S17: C ✔ / O – / K – | T17: Regulatory design failure — not closable by a tool. | U17: https://library.mevaker.gov.il/sites/DigitalLibrary/Documents/2024/2024.01-74A/2024-74A-305-Water-Taagid.pdf
A18: 17 | B18: Employers of reservists — reimbursement of social contributions (20% of daily wage) | C18: n/q | D18: n/q — take-up not in visible abstract; mechanism temporary to end-2024, extended to end-2025 (p.18). | E18: n/q | F18: Temporary statutory mechanism; awareness among small employers (your candidate) not quantified in the abstract. | G18: ביטוח לאומי; משרד האוצר | H18: Unknown | I18: 3 | J18: =IFERROR(INDEX('Legend & Method'!$C$11:$C$14,MATCH(H18,'Legend & Method'!$B$11:$B$14,0)),"") -> 0.75 | K18: =IF(ISNUMBER(C18),C18*J18*I18,"n/q") -> n/q | L18: =IF(ISNUMBER(K18),RANK(K18,$K$2:$K$23),"—") -> — | M18: Comptroller reservists report Nov 2025 ch.1 | N18: 18 | O18: שיפוי מעסיקים בגין ההפרשות הסוציאליות … | P18: Fetch-verified (mechanism only) | Q18: — | R18: מילואים 0.95M | S18: C ~ / O – / K ✔ | T18: Your candidate #2 — no take-up number in the abstract; 2026 status of the mechanism unknown. | U18: https://library.mevaker.gov.il/sites/DigitalLibrary/Documents/2025/Reservists/2025-Reservists-All-Report-HE.pdf
A19: 18 | B19: Reservist students not refunded tuition / registration fees | C19: n/q | D19: n/q — 3 of 25 institutions (12%) did not fully refund tuition; 32% did not fully refund registration fees (p.9). ~60,000 student reservists. | E19: n/q; institutions used ₪124M of ₪195M support budget (press release) | F19: Institutional non-compliance with מל"ג guidance. | G19: מל"ג/ות"ת; מוסדות להשכלה גבוהה | H19: Unknown | I19: 3 | J19: =IFERROR(INDEX('Legend & Method'!$C$11:$C$14,MATCH(H19,'Legend & Method'!$B$11:$B$14,0)),"") -> 0.75 | K19: =IF(ISNUMBER(C19),C19*J19*I19,"n/q") -> n/q | L19: =IF(ISNUMBER(K19),RANK(K19,$K$2:$K$23),"—") -> — | M19: Comptroller reservists report Nov 2025 ch.2 | N19: 9 (foreword) | O19: 12% ממוסדות הלימוד (3 מ-25 המוסדות) לא נתנו החזר מלא של שכר הלימוד | P19: Fetch-verified verbatim | Q19: — | R19: מילואים 0.95M | S19: C ✔ / O – / K ✔ | T19: Small, institution-specific. | U19: https://library.mevaker.gov.il/sites/DigitalLibrary/Documents/2025/Reservists/2025-Reservists-All-Report-HE.pdf
A20: 19 | B20: Adults with post-Oct-7 mental-health symptoms not in care | C20: n/q | D20: n/q as a gap: ~3M adults with moderate–severe PTSD/depression/anxiety symptoms (Apr 2024 survey, pp.2–23); 11% of hotel evacuees treated; projected demand 680,000 vs capacity 340,000. | E20: n/q | F20: No systematic identification; 6.5-month waits at health funds; response 'ברובו המוחלט על מתנדבים'. | G20: משרד הבריאות; קופות החולים; ביטוח לאומי; מרכזי חוסן | H20: Partial | I20: 3 | J20: =IFERROR(INDEX('Legend & Method'!$C$11:$C$14,MATCH(H20,'Legend & Method'!$B$11:$B$14,0)),"") -> 0.5 | K20: =IF(ISNUMBER(C20),C20*J20*I20,"n/q") -> n/q | L20: =IF(ISNUMBER(K20),RANK(K20,$K$2:$K$23),"—") -> — | M20: Comptroller special report Feb 2025 — הטיפול בבריאות הנפש | N20: 2–23 (abstract) | O20: — | P20: Fetch-verified (abstract) | Q20: משרד הבריאות 687 complaints 2025 (43%) | R20: בריאות ומחלות 1.32M (↑1) | S20: C ✔ / O ~ / K ✔ | T20: Health-basket/Tofes-17 appeals (your candidate #5) do not appear as a quantified Comptroller finding in 2023–26. | U20: https://library.mevaker.gov.il/sites/DigitalLibrary/Documents/2025/Swords-of-Iron-1/2025-Swords-of-Iron-100.pdf
A21: 20 | B21: War-wounded: recognition backlog at אגף השיקום; NII benefits unpaid | C21: n/q | D21: Agent-reported from the Jun 2026 report: ~7,000 recognition applications pending, 2,200 >1 yr; ~₪62M NII benefits unpaid (2024). NOT confirmed in the fetched pp.1–29 (which cover rehab capacity). | E21: ~₪62M (agent-reported) | F21: Administrative backlog; patients not told of rehab options. | G21: משרד הביטחון – אגף השיקום; ביטוח לאומי; משרד הבריאות | H21: Unknown | I21: 2 | J21: =IFERROR(INDEX('Legend & Method'!$C$11:$C$14,MATCH(H21,'Legend & Method'!$B$11:$B$14,0)),"") -> 0.75 | K21: =IF(ISNUMBER(C21),C21*J21*I21,"n/q") -> n/q | L21: =IF(ISNUMBER(K21),RANK(K21,$K$2:$K$23),"—") -> — | M21: Comptroller special report 'פצע פתוח' Jun 2026 — ch. 102 | N21: n/v | O21: — | P21: Agent-reported only — verify | Q21: MoD/IDF complaints rising (R51 p.21, R52 p.28) | R21: אנשים עם מוגבלות 2.97M | S21: C ? / O ~ / K ~ | T21: Backlog, not take-up. | U21: https://library.mevaker.gov.il/sites/DigitalLibrary/Documents/2026/Swords-of-Iron/2026-Swords-of-Iron-102.pdf
A22: 21 | B22: People with disabilities — local authorities unable to supply mandated services | C22: n/q | D22: n/q as a gap: 1.6M people with disabilities (2020); only 23% of authorities can supply all mandated services; 7× gap in social-worker posts periphery vs centre (pp.433–456). | E22: ₪3.3B allocation 2020 | F22: Supply-side: staffing, policy vacuum, reactive rather than proactive identification. | G22: משרד הרווחה; רשויות מקומיות | H22: N | I22: 1 | J22: =IFERROR(INDEX('Legend & Method'!$C$11:$C$14,MATCH(H22,'Legend & Method'!$B$11:$B$14,0)),"") -> 1 | K22: =IF(ISNUMBER(C22),C22*J22*I22,"n/q") -> n/q | L22: =IF(ISNUMBER(K22),RANK(K22,$K$2:$K$23),"—") -> — | M22: Comptroller שלטון מקומי Jul 2023 — ch. 201 | N22: 433–456 | O22: — | P22: Fetch-verified (abstract) | Q22: — | R22: אנשים עם מוגבלות 2.97M (#3) | S22: C ✔ / O – / K ✔✔ | T22: Supply-side. | U22: https://library.mevaker.gov.il/sites/DigitalLibrary/Documents/2023/2023-Shilton/2023-Shilton-201-Disabled.pdf
A23: 22 | B23: OUT OF WINDOW (2021): unclaimed tax benefits / social rights — ₪3.6B by ~2M citizens | C23: n/q | D23: Not scored — published 2021 (72א), outside the 2023–2026 window. Listed because Kol Zchut demand is strongest here (מיסים 3.21M; מענק עבודה 250K views; נקודות זיכוי 180K). | E23: ₪3.6B (2021 report) | F23: Awareness; active filing required (מענק עבודה, נקודות זיכוי, החזרי מס). | G23: רשות המסים; ביטוח לאומי | H23: Unknown | I23: 5 | J23: =IFERROR(INDEX('Legend & Method'!$C$11:$C$14,MATCH(H23,'Legend & Method'!$B$11:$B$14,0)),"") -> 0.75 | K23: =IF(ISNUMBER(C23),C23*J23*I23,"n/q") -> n/q | L23: =IF(ISNUMBER(K23),RANK(K23,$K$2:$K$23),"—") -> — | M23: Comptroller 72א (2021) — מיצוי הטבות מס ברשות המיסים: מעקב מורחב; אי-מיצוי זכויות חברתיות: ביקורת מעקב | N23: n/v | O23: — | P23: Agent-reported; out of window | Q23: רשות המסים 1,119 (2025) | R23: מיסים 3.21M (#2); מענק עבודה 250K (#4 page) | S23: C (2021) / O ✔ / K ✔✔ | T23: If you relax the window, this is the largest cell in the country. Decision for you. | U23: https://library.mevaker.gov.il/sites/DigitalLibrary/Pages/Reports/7336-15.aspx

Sheet Legend & Method
A1: Impact Week — Phase 1 impact map (built Mon 14 Sep 2026)
A3: Method
A4: Source universe: State Comptroller (מבקר המדינה) and Ombudsman (נציב תלונות הציבור) reports published Jan 2023 – Sep 2026 that deal with מיצוי זכויות / שירות לאזרח (inventory: 50 items, see 'Inventory' sheet).
A5: Each row on 'Map' is one documented finding. Population = people the SOURCE documents as not receiving the right (not the whole eligible population). 'n/q' = the source does not quantify it; no estimate was substituted.
A6: Score = Population × Unfixed factor × Buildable (people-first ranking, as agreed Mon morning). NIS at stake is shown but is a tiebreak, not a multiplier — population cancels out of the original people × NIS-per-person formula.
A7: Overlays: Ombudsman complaint volume against the responsible body (sheet 'Ombudsman'), Kol Zchut 2025 topic/page views (sheet 'Demand – Kol Zchut'). Google Trends was not reachable from the sandbox.
A9: Unfixed factor (blue = editable assumption)
B10: Fixed? | C10: Factor | D10: Meaning
B11: N | C11: 1 | D11: Source says not fixed / follow-up audit says הליקוי לא תוקן
B12: Unknown | C12: 0.75 | D12: No follow-up audit found; status after report unknown
B13: Partial | C13: 0.5 | D13: Temporary or partial fix documented
B14: Y | C14: 0 | D14: Fixed or programme expired
A16: Buildable scale (1–5)
B17: 5 | C17: A matcher / letter generator directly closes the gap using the existing public corpus (Kol Zchut, BTL, municipality forms).
B18: 4 | C18: Matcher helps a lot but one step outside the tool is still required (visit, document, committee).
B19: 3 | C19: Tool helps at the margin, or the exact claim process must be verified before building.
B20: 2 | C20: Gap is mostly supply-side or administrative backlog; a tool can only generate complaints / status checks.
B21: 1 | C21: Legislative, budgetary, or no legal entitlement exists — not buildable in 3 days.
A23: Caveats (read before trusting a number)
A24: 1. Verification levels (column 'Verification status'): PDF-VERIFIED = the full PDF was read through Harel's browser (pdf.js text extraction) and the quote/page checked verbatim — applies to the 7 finalist reports: aging ch.104, seniors 2023, electricity 74א, נפש אחת 74א, reservists ch.1, Ombudsman 52, Ombudsman elderly 2023. Fetch-verified = only the first ~25 pages (the official תקציר) were readable from the sandbox. Agent-reported = taken from a research agent's reading, not re-checked.
A25: 2. Page numbers are PRINTED page numbers (annual-report chapters carry the volume's numbering, e.g. 1209; standalone special reports start at 1). Where a body table has no printed number the PDF page index is given as 'PDF p.N'.
A26: 3. 'Derived' in the Population-basis column means one subtraction or multiplication of two figures that both appear in the source (e.g. 450,000 retirees − 17,428 attendees). Nothing else was computed; nothing was estimated.
A27: 4. Rows whose population is n/q are NOT ranked. They are listed so the qualitative case (esp. arnona) is visible; they can enter the ranking once a source gives a count.
A28: 5. Out-of-window item: 72א (2021) 'אי-מיצוי זכויות חברתיות' / 'מיצוי הטבות מס' (₪3.6B unclaimed tax benefits, ~2M people) is the direct predecessor of this map. Listed on 'Map' as unscored for transparency.

Sheet Ombudsman
A1: Year | B1: Body | C1: Complaints filed | D1: % justified | E1: Source | F1: Page
A2: 2023 | B2: TOTAL | C2: 22356 | D2: 43% justified/rectified; 33% among decided | E2: https://www.mevaker.gov.il/newsroom/2024-06-24 ; https://library.mevaker.gov.il/sites/DigitalLibrary/Documents/2024/2024-NTZ-50-Taktzir-EN.pdf | F2: R50 p.4; R50-EN pp.10,12
A3: 2023 | B3: משרד התחבורה | C3: 2081 | D3: n/s | E3: https://library.mevaker.gov.il/sites/DigitalLibrary/Documents/2024/2024-NTZ-50-Taktzir-EN.pdf | F3: 11–12
A4: 2023 | B4: המוסד לביטוח לאומי | C4: 1528 | D4: n/s (<33%) | E4: https://library.mevaker.gov.il/sites/DigitalLibrary/Documents/2024/2024-NTZ-50-Taktzir-EN.pdf | F4: 11–12
A5: 2023 | B5: רשות האוכלוסין | C5: 1021 | D5: 49.1% | E5: https://library.mevaker.gov.il/sites/DigitalLibrary/Documents/2024/2024-NTZ-50-Taktzir-EN.pdf | F5: 11–13
A6: 2023 | B6: משרד העבודה | C6: 860 | D6: 43.6% | E6: https://library.mevaker.gov.il/sites/DigitalLibrary/Documents/2024/2024-NTZ-50-Taktzir-EN.pdf | F6: 11–13
A7: 2023 | B7: רשות המסים | C7: 798 | D7: n/s | E7: https://library.mevaker.gov.il/sites/DigitalLibrary/Documents/2024/2024-NTZ-50-Taktzir-EN.pdf | F7: 11–12
A8: 2023 | B8: דואר ישראל | C8: 708 | D8: 40.9% | E8: https://library.mevaker.gov.il/sites/DigitalLibrary/Documents/2024/2024-NTZ-50-Taktzir-EN.pdf | F8: 11–13
A9: 2023 | B9: משטרת ישראל | C9: 673 | D9: n/s | E9: https://library.mevaker.gov.il/sites/DigitalLibrary/Documents/2024/2024-NTZ-50-Taktzir-EN.pdf | F9: 11–12
A10: 2023 | B10: משרד החינוך | C10: 621 | D10: 69.1% | E10: https://library.mevaker.gov.il/sites/DigitalLibrary/Documents/2024/2024-NTZ-50-Taktzir-EN.pdf | F10: 11–13
A11: 2023 | B11: משרד הבריאות | C11: 616 | D11: 66.3% | E11: https://library.mevaker.gov.il/sites/DigitalLibrary/Documents/2024/2024-NTZ-50-Taktzir-EN.pdf | F11: 11–13
A12: 2023 | B12: חברת החשמל | C12: 558 | D12: n/s | E12: https://library.mevaker.gov.il/sites/DigitalLibrary/Documents/2024/2024-NTZ-50-Taktzir-EN.pdf | F12: 11–12
A13: 2023 | B13: גופי השלטון המקומי (total) | C13: 5183 | D13: — (R51 chart 17 says 4,730 — discrepancy) | E13: https://www.mevaker.gov.il/newsroom/2024-06-24 | F13: R51 p.38
... A25: 2024 | B25: משרד הבריאות | C25: 594 | D25: 40.1% | E25: https://library.mevaker.gov.il/sites/DigitalLibrary/Documents/2025/2025-NTZ-51.pdf | F25: 20–21
A26: 2024 | B26: משרד הביטחון | C26: n/v (+31% YoY) | D26: — | E26: https://library.mevaker.gov.il/sites/DigitalLibrary/Documents/2025/2025-NTZ-51.pdf | F26: 21
A27: 2024 | B27: גופי השלטון המקומי (total) | C27: 4739 | D27: 24% of complaints | E27: https://library.mevaker.gov.il/sites/DigitalLibrary/Documents/2025/2025-NTZ-51.pdf | F27: 38
A28: 2025 | B28: TOTAL | C28: 30366 | D28: 56% among decided (6,021 of 10,672); 7,429 rectified without ruling | E28: https://library.mevaker.gov.il/sites/DigitalLibrary/Documents/2026/2026-NTZ-52.pdf | F28: 24, 31
A29: 2025 | B29: משרד העבודה (סבסוד מעונות) | C29: 7082 | D29: 91% (6,931 vs האגף לעידוד תעסוקת הורים, 90.8%) | E29: https://library.mevaker.gov.il/sites/DigitalLibrary/Documents/2026/2026-NTZ-52.pdf | F29: 24, 26
A30: 2025 | B30: משרד התחבורה | C30: 2298 | D30: 26% | E30: https://library.mevaker.gov.il/sites/DigitalLibrary/Documents/2026/2026-NTZ-52.pdf | F30: 26
A31: 2025 | B31: המוסד לביטוח לאומי | C31: 1581 | D31: 7% | E31: https://library.mevaker.gov.il/sites/DigitalLibrary/Documents/2026/2026-NTZ-52.pdf | F31: 26–27
A32: 2025 | B32: רשות המסים | C32: 1119 | D32: 10% | E32: https://library.mevaker.gov.il/sites/DigitalLibrary/Documents/2026/2026-NTZ-52.pdf | F32: 26
A33: 2025 | B33: רשות האוכלוסין | C33: 994 | D33: 47% | E33: https://library.mevaker.gov.il/sites/DigitalLibrary/Documents/2026/2026-NTZ-52.pdf | F33: 26
A34: 2025 | B34: משרד החינוך | C34: 940 | D34: 33% | E34: https://library.mevaker.gov.il/sites/DigitalLibrary/Documents/2026/2026-NTZ-52.pdf | F34: 26
A35: 2025 | B35: משטרת ישראל | C35: 932 | D35: 35% | E35: https://library.mevaker.gov.il/sites/DigitalLibrary/Documents/2026/2026-NTZ-52.pdf | F35: 26
A36: 2025 | B36: משרד הבריאות | C36: 687 | D36: 43% | E36: https://library.mevaker.gov.il/sites/DigitalLibrary/Documents/2026/2026-NTZ-52.pdf | F36: 26
A37: 2025 | B37: עיריית ירושלים | C37: 609 | D37: 34% | E37: https://library.mevaker.gov.il/sites/DigitalLibrary/Documents/2026/2026-NTZ-52.pdf | F37: 26
A38: 2025 | B38: משרד המשפטים | C38: 550 | D38: 29% | E38: https://library.mevaker.gov.il/sites/DigitalLibrary/Documents/2026/2026-NTZ-52.pdf | F38: 26
A39: 2025 | B39: המשרד לביטחון לאומי | C39: 248 | D39: — (−83%) | E39: https://library.mevaker.gov.il/sites/DigitalLibrary/Documents/2026/2026-NTZ-52.pdf | F39: 28
A40: 2025 | B40: צה"ל / משרד הרווחה / קופ"ח מאוחדת | C40: n/v (+54% / +69% / +63%) | D40: — | E40: https://library.mevaker.gov.il/sites/DigitalLibrary/Documents/2026/2026-NTZ-52.pdf | F40: 28
A41: 2025 | B41: גופי השלטון המקומי | C41: ≈20% of complaints (count n/v) | D41: — | E41: https://library.mevaker.gov.il/sites/DigitalLibrary/Documents/2026/2026-NTZ-52.pdf | F41: 25
A42: 2025 | B42: R52 chart 3 (p.26) — top-10 bodies 2023/2024/2025 | C42: משרד העבודה 860/934/7,082 · תחבורה 2,081/1,759/2,298 · ביטוח לאומי 1,528/1,212/1,581 · רשות המסים 798/787/1,119 · רשות האוכלוסין 1,021/797/994 · חינוך 621/714/940 · משטרה 673/720/932 · בריאות 616/594/687 · ירושלים 522/455/609 · משפטים 477/507/550 | D42: 2025: 91% / 26% / 7% / 10% / 33% / 35% / 43% … | E42: https://library.mevaker.gov.il/sites/DigitalLibrary/Documents/2026/2026-NTZ-52.pdf | F42: 26 (PDF-verified)
A43: 2025 | B43: המוסד לביטוח לאומי (appendix) | C43: 1,566 / 1,677 | D43: 7.1% (36 of 505 decided) | E43: https://library.mevaker.gov.il/sites/DigitalLibrary/Documents/2026/2026-NTZ-52.pdf | F43: 136 (PDF-verified; column semantics not decoded)
A44: 2025 | B44: משרד הביטחון (appendix) | C44: 267 / 286 | D44: 48% (36 of 75) | E44: https://library.mevaker.gov.il/sites/DigitalLibrary/Documents/2026/2026-NTZ-52.pdf | F44: 130 (PDF-verified)
A45: 2025 | B45: — of which אגף שיקום נכים | C45: 191 / 211 | D45: 53.2% (33 of 62) | E45: https://library.mevaker.gov.il/sites/DigitalLibrary/Documents/2026/2026-NTZ-52.pdf | F45: 130 (PDF-verified)
A46: 2025 | B46: משרד הרווחה והביטחון החברתי (appendix) | C46: 210 / 210 | D46: 24.1% (7 of 29) | E46: https://library.mevaker.gov.il/sites/DigitalLibrary/Documents/2026/2026-NTZ-52.pdf | F46: 134 (PDF-verified)
A47: 2025 | B47: עיריית ירושלים (appendix) | C47: 588 / 608 | D47: 34.1% (46 of 135) | E47: https://library.mevaker.gov.il/sites/DigitalLibrary/Documents/2026/2026-NTZ-52.pdf | F47: 143 (PDF-verified)
A48: 2025 | B48: משרתי מילואים (topic) | C48: n/v (the '211' quoted in press matches אגף שיקום נכים above) | D48: — | E48: https://library.mevaker.gov.il/sites/DigitalLibrary/Documents/2026/2026-NTZ-52.pdf | F48: 9, 48 (section exists; count not in text)
A49: 1/2023–11/2025 | B49: ארנונה (special report) | C49: 937 | D49: 40%; discounts/exemptions 41.8% of complaints, 41.6% justified; ₪376,508 recovered | E49: https://library.mevaker.gov.il/sites/DigitalLibrary/Documents/2026/2026-Ombudsman-Arnona.pdf | F49: 12–17
A50: 2019–mid-2022 | B50: Complaints by people 65+ (special report) | C50: 12882 | D50: 41.5% (2021, service complaints); 13.2% Holocaust survivors (p.20); by body p.15: משטרה 6,128 · רשות המסים 3,928 · עמידר 2,919 · משרד הבריאות 2,145 · דואר 1,857 · תחבורה 1,133 · ביטוח לאומי 988 | E50: https://library.mevaker.gov.il/sites/DigitalLibrary/Documents/2023/2023-NTZ-3rd-Age.pdf | F50: 11, 15, 20 (PDF-verified)
A52: Notes: n/s = not shown (below the 33% threshold chart); n/v = not visible in fetched pages (appendices with full per-body tables were beyond the ~25-page fetch limit: R50 pp.226–243, R51 pp.104–122, R52 pp.43–46). RTL charts were decoded by the research agent and cross-checked against press releases and N12; treat as provisional until the PDFs are opened locally. Topic mix 2025 (R52 chart 5, p.29): public service 8,839 (29%); daycare subsidies 5,691 (19%); education 1,969; taxes 1,126; grants 1,118; health 1,078; benefits 983.

Sheet Demand – Kol Zchut
A1: Kol Zchut 2025 — top-20 topic areas (Hebrew site), page views and rank change vs 2024
A2: Site 2025: 25.6M visits · 11M unique users · 38M page views · 3.25M referrals to gov sites · 630K form clicks · chatbot ~700K questions/yr. Source: https://www.kolzchut.org.il/w/he/images/5/50/%D7%9B%D7%9C_%D7%96%D7%9B%D7%95%D7%AA_-_%D7%A1%D7%99%D7%9B%D7%95%D7%9D_2025.pdf
A3: Rank | B3: Topic | C3: Views 2025 | D3: Δ rank vs 2024 | E3: Relevance to map rows
A4: 1 | B4: תעסוקה וזכויות עובדים | C4: 7470000 | D4: –
A5: 2 | B5: מיסים | C5: 3210000 | D5: – | E5: tax benefits (out of window); arnona buried here
A6: 3 | B6: אנשים עם מוגבלות | C6: 2970000 | D6: – | E6: veterans, adults w/ disabilities
A7: 4 | B7: פנסיה וחסכון ארוך טווח | C7: 1960000 | D7: – | E7: retirees
A8: 5 | B8: דיור ושיכון | C8: 1770000 | D8: +1 | E8: public housing; arnona
A9: 6 | B9: בריאות ומחלות | C9: 1320000 | D9: +1 | E9: mental health
A10: 7 | B10: חינוך | C10: 1280000 | D10: +2
A11: 8 | B11: מצב חירום | C11: 1160000 | D11: −3 | E11: evacuees, second circle
A12: 9 | B12: הכנסה נמוכה וקשיים כלכליים | C12: 1130000 | D12: +7 | E12: income supplement, discounts
A13: 10 | B13: עצמאים ובעלי עסקים | C13: 1080000 | D13: +3 | E13: self-employed reservists; small-business aid
A14: 11 | B14: נשים | C14: 1070000 | D14: −1
A15: 12 | B15: זיקנה והזדקנות | C15: 1060000 | D15: +2 | E15: RETIREE CELL
A16: 13 | B16: משפחה | C16: 1050000 | D16: +8 | E16: daycare subsidies
A17: 14 | B17: צרכנות | C17: 1030000 | D17: −2 | E17: electricity discount
A18: 15 | B18: מילואים | C18: 950000 | D18: −7 | E18: reservist rows (1.5M, #8 in 2024)
A19: 16 | B19: חובות | C19: 930000 | D19: −1
A20: 17 | B20: אזרחות ותושבות | C20: 700000 | D20: –
A21: 18 | B21: נהיגה ותעבורה | C21: 600000 | D21: +1
A22: 19 | B22: סוף החיים | C22: 540000 | D22: −1
A23: 20 | B23: ילדים ונוער | C23: 500000 | D23: –
A25: Top-10 individual pages 2025 (Hebrew)
A26: 1 | B26: דמי הבראה | C26: 480000
A27: 2 | B27: שכר מינימום | C27: 400000
A28: 3 | B28: מדרגות מס הכנסה | C28: 386000
A29: 4 | B29: מענק עבודה (מס הכנסה שלילי) | C29: 250000
A30: 5 | B30: הגבלת רעש מדירות שכנים | C30: 221000
A31: 6 | B31: דמי אבטלה | C31: 215000
A32: 7 | B32: חובת ביטוח פנסיוני לעובדים | C32: 203000
A33: 8 | B33: הודעה מוקדמת להתפטרות | C33: 190000
A34: 9 | B34: קרן השתלמות | C34: 180000
A35: 10 | B35: נקודות זיכוי ממס הכנסה | C35: 180000
A37: 2024 (source: https://www.kolzchut.org.il/w/he/images/e/ec/%D7%9B%D7%9C-%D7%96%D7%9B%D7%95%D7%AA_-_%D7%A1%D7%99%D7%9B%D7%95%D7%9D_2024.pdf): #1 page = פורטל חרבות ברזל 770K; מילואים topic 1.5M (rank 8); מצב חירום 2.6M; emergency portal's most-viewed page: 'תשלום עבור שירות מילואים'; BTL calculator clicks 4M (+23%).
A38: Russian-site top pages 2025 are BTL old-age benefits: זכותון קצבת זקנה 43.4K; מענק עבודה 40.5K; תוספת השלמת הכנסה לקצבת זקנה 32.7K; קצבת נכות כללית 18.4K.
A39: Not published with any count: ארנונה, סל הבריאות/ועדת חריגים, גמלת סיעוד, טופס 17. Live per-page stats (Special:PopularPages, API) are blocked by robots.txt — not bypassed.
A40: Google Trends: blocked at the sandbox proxy (403 on CONNECT) — no data; run pytrends from an unrestricted machine if wanted (script in scratchpad).

Sheet Inventory
A1: # | B1: Report / chapter (HE) | C1: Type | D1: Published | E1: Topic / population | F1: Responsible body | G1: PDF URL | H1: URL confidence
A2: 1 | B2: אתגרים ויעדים במתן שירות לבני הגיל השלישי – לקחים מבירור תלונות | C2: Ombudsman special | D2: Feb 2023 | E2: Elderly 65+: bureaucratic/digital barriers, low awareness; 13% Holocaust survivors | F2: משטרה, רשות המיסים, עמידר, משרד הבריאות, ביטוח לאומי | G2: https://library.mevaker.gov.il/sites/DigitalLibrary/Documents/2023/2023-NTZ-3rd-Age.pdf | H2: V
A3: 2 | B3: השמת ילדים בסיכון בפנימיות, באומנה ובאימוץ | C3: Annual May 2023 | D3: May 2023 | E3: Children at risk: 87% in foster care without care plans | F3: משרד הרווחה | G3: https://library.mevaker.gov.il/sites/DigitalLibrary/Documents/2023/2023.5/2023.5-104-Omna-Imutz.pdf | H3: S
A4: 3 | B4: שירותי בריאות השן | C4: Annual May 2023 | D4: May 2023 | E4: Public dental entitlement | F4: משרד הבריאות | G4: https://library.mevaker.gov.il/sites/DigitalLibrary/Documents/2023/2023.5/2023.5-207-Dental-Health.pdf | H4: S
A5: 4 | B5: המרכז לגביית קנסות | C5: Annual May 2023 | D5: May 2023 | E5: Service to debtors | F5: רשות האכיפה והגבייה | G5: https://library.mevaker.gov.il/sites/DigitalLibrary/Documents/2023/2023.5/2023.5-301-Achifa-Gviya-Taktzir.pdf | H5: S
A6: 5 | B6: נציב תלונות הציבור – דוח שנתי 49 (2022) | C6: Ombudsman annual | D6: Jun 2023 | E6: 20,938 complaints, 44% justified | F6: כלל הגופים | G6: https://library.mevaker.gov.il/sites/DigitalLibrary/Documents/2023/NTZ-49/NTZ-49-Full-Report.pdf | H6: V
A7: 6 | B7: ארנונה – אסדרה, הטלה ומתן הנחות | C7: Annual שלטון מקומי | D7: Jul 2023 | E7: Arnona discounts ₪8.8B/yr; no procedures; irregular NII feed | F7: משרד הפנים + 6 רשויות | G7: https://library.mevaker.gov.il/sites/DigitalLibrary/Documents/2023/2023-Shilton/2023-Shilton-103-Arnona-Asdara.pdf | H7: V
A8: 7 | B8: ארנונה – השירות לתושב | C8: Annual שלטון מקומי | D8: Jul 2023 | E8: 25,200 abandoned calls; 34% online requests late | F8: 6 רשויות | G8: https://library.mevaker.gov.il/sites/DigitalLibrary/Documents/2023/2023-Shilton/2023-Shilton-104-Arnona-Sherut.pdf | H8: V
A9: 8 | B9: השירותים לאנשים עם מוגבלות – מרכז מול פריפריה | C9: Annual שלטון מקומי | D9: Jul 2023 | E9: 1.6M disabled; 23% of authorities supply all services | F9: משרד הרווחה + 6 רשויות | G9: https://library.mevaker.gov.il/sites/DigitalLibrary/Documents/2023/2023-Shilton/2023-Shilton-201-Disabled.pdf | H9: V
A10: 9 | B10: טיפול הרשויות המקומיות באזרחים הוותיקים | C10: Annual שלטון מקומי | D10: Jul 2023 | E10: 42% unaware of services; arnona 30% vs 25% | F10: משרד הרווחה, שוויון חברתי + 9 רשויות | G10: https://library.mevaker.gov.il/sites/DigitalLibrary/Documents/2023/2023-Shilton/2023-Shilton-202-Vatikim.pdf | H10: V
A11: 10 | B11: השירות לציבור בחברת החשמל | C11: Annual 74א | D11: Jan 2024 | E11: 158,000 of 471,000 eligible don't get the discount | F11: חח"י, רשות החשמל | G11: https://library.mevaker.gov.il/sites/DigitalLibrary/Documents/2024/2024.01-74A/2024-74A-303-Electric.pdf | H11: V
A12: 11 | B12: תאגידי המים והביוב – ביקורת מעקב | C12: Annual 74א | D12: Jan 2024 | E12: ₪225–243M water relief unused 2015–21 | F12: רשות המים, משרד הפנים | G12: https://library.mevaker.gov.il/sites/DigitalLibrary/Documents/2024/2024.01-74A/2024-74A-305-Water-Taagid.pdf | H12: V
A13: 12 | B13: רפורמת 'נפש אחת' – נכי צה"ל | C13: Annual 74א | D13: Jan 2024 | E13: 74–80% unaware; 30% budget execution | F13: משרד הביטחון – אגף השיקום | G13: https://library.mevaker.gov.il/sites/DigitalLibrary/Documents/2024/2024.01-74A/2024-74A-401-Nefesh1.pdf | H13: V
... A51: 50 | B51: זנות וסחר בבני אדם – הגנה על קורבנות | C51: Special | D51: Jul 2026 | E51: Victim services insufficient | F51: משרד הרווחה, משרד המשפטים | G51: https://library.mevaker.gov.il/sites/DigitalLibrary/Documents/2026/Prostitution-and-Human-Trafficking/2026-Prostitution-and-Human-Trafficking.pdf | H51: V
A53: Confidence: V = URL taken from a fetched library page/PDF; S = URL seen only in a search snippet; N = PDF URL not located. Excluded as off-topic after TOC check: Feb 2023 & Dec 2025 (defence), May 2024, May 2026 annual, 'הדרום הפרוע', 'נתונים להשפעה', 'מעון לדאגה', Jun 2026 שלטון מקומי. Library search pages are JS-only; enumeration was done via publication pages, chapter pages, abstracts books and newsroom releases (list in Sources).

Sheet Sources
A1: Source | B1: URL / detail
A2: Comptroller newsroom — reservists report (18.11.2025) | B2: https://www.mevaker.gov.il/newsroom/2025-11-18-special-report
A3: Comptroller newsroom — arnona Ombudsman report (3.2.2026) | B3: https://www.mevaker.gov.il/newsroom/2026-02-03-arnona
A4: Ombudsman press releases 2023 / 2024 / 2025 reports | B4: https://www.mevaker.gov.il/newsroom/2024-06-24 | https://www.mevaker.gov.il/newsroom/2025-07-01-ntz | https://www.mevaker.gov.il/newsroom/2026-05-19-ombudsman-annual-report
A5: Calcalist — 4,400 self-employed reservists / ₪37M | B5: https://www.calcalist.co.il/local_news/article/bkk2z6ulzg
A6: Kol Zchut summaries 2025 / 2024 | B6: https://www.kolzchut.org.il/w/he/images/5/50/%D7%9B%D7%9C_%D7%96%D7%9B%D7%95%D7%AA_-_%D7%A1%D7%99%D7%9B%D7%95%D7%9D_2025.pdf | https://www.kolzchut.org.il/w/he/images/e/ec/%D7%9B%D7%9C-%D7%96%D7%9B%D7%95%D7%AA_-_%D7%A1%D7%99%D7%9B%D7%95%D7%9D_2024.pdf
A7: Kol Zchut about page (13M users 2025) | B7: https://www.kolzchut.org.il/he/כל_זכות:אודות
A8: Library publication pages used | B8: /Pages/Publications/ 890, 893, 892, 899, 907, 923, 922, 937, 975, 921, 1069, 1220, 1261, 1461, 1663, 2026, 2070, 2144, 2154, 2155, 2157
A9: Library chapter-page ID series used | B9: /Pages/Reports/ 7650, 7698, 7746, 7786, 7845, 8242, 8792, 9139, 9194, 9561, 10387, 10572, 10593, 10606, 10607, 10630
A10: Blocked from sandbox | B10: curl/pytrends to library.mevaker.gov.il, fs.knesset.gov.il, trends.google.com (proxy 403); Kol Zchut Special pages & API (robots.txt, not bypassed)
